fts/__init__.py
fts/__main__.py
fts/fts.py
fts/opensubs.py
fts-1.1.0.dist-info/DESCRIPTION.rst
fts-1.1.0.dist-info/METADATA
fts-1.1.0.dist-info/RECORD
fts-1.1.0.dist-info/WHEEL
fts-1.1.0.dist-info/entry_points.txt
fts-1.1.0.dist-info/metadata.json
fts-1.1.0.dist-info/top_level.txt
