Metadata-Version: 2.0
Name: fts
Version: 1.1.0
Summary: Instantly find subtitles via the command line
Home-page: https://github.com/sereneblue/fts
Author: sereneblue
Author-email: UNKNOWN
License: GPLv3
Keywords: subtitles,opensubtitles,subscene,cli
Platform: UNKNOWN
Classifier: Intended Audience :: Developers
Classifier: Environment :: Console
Classifier: Topic :: Utilities
Classifier: License :: OSI Approved :: GNU General Public License v3 (GPLv3)
Classifier: Natural Language :: English
Classifier: Operating System :: OS Independent
Classifier: Programming Language :: Python :: 3
Classifier: Programming Language :: Python :: 3.2
Classifier: Programming Language :: Python :: 3.3
Classifier: Programming Language :: Python :: 3.4
Classifier: Programming Language :: Python :: 3.5
Classifier: Programming Language :: Python :: 3.6
Requires-Dist: docopt
Requires-Dist: requests
